BlockSDK/__init__.py
BlockSDK/avalanche.py
BlockSDK/base.py
BlockSDK/binancesmart.py
BlockSDK/blocksdk.py
BlockSDK/ethereum.py
BlockSDK/ethereumclassic.py
BlockSDK/klaytn.py
BlockSDK/polygon.py
BlockSDK-3.0.0.dist-info/LICENSE
BlockSDK-3.0.0.dist-info/METADATA
BlockSDK-3.0.0.dist-info/WHEEL
BlockSDK-3.0.0.dist-info/top_level.txt
BlockSDK-3.0.0.dist-info/RECORD
