Metadata-Version: 2.1
Name: BlockSDK
Version: 3.0.0
Summary: BlockSDK is an API service for blockchain applications
Home-page: https://blocksdk.com
Download-URL: https://github.com/Block-Chen/blocksdk-python
Author: BlockChen
Author-email: bianconery@blockchen.io
Keywords: blocksdk api
Classifier: Programming Language :: Python :: 3
Classifier: Programming Language :: Python :: 3.7
Classifier: Programming Language :: Python :: 3.8
Classifier: Programming Language :: Python :: 3.9
Requires-Python: >=3
License-File: LICENSE
Requires-Dist: requests
